peoplecodeparser/PeopleCodeLexer.py
peoplecodeparser/PeopleCodeParser.py
peoplecodeparser/PeopleCodeParserListener.py
peoplecodeparser/PeopleCodeParserVisitor.py
peoplecodeparser/__init__.py
peoplecodeparser-1.1.6.dist-info/LICENSE.txt
peoplecodeparser-1.1.6.dist-info/METADATA
peoplecodeparser-1.1.6.dist-info/WHEEL
peoplecodeparser-1.1.6.dist-info/top_level.txt
peoplecodeparser-1.1.6.dist-info/RECORD
