Metadata-Version: 2.1
Name: peoplecodeparser
Version: 1.1.6
Summary: A PeopleCode parser built with ANTLR 4
Home-page: https://github.com/lbaca/PeopleCodeParser
Author: Leandro Baca
Author-email: leandrobaca77@gmail.com
Keywords: parser peoplesoft peoplecode source application-class application-package antlr antlr4
Classifier: Development Status :: 5 - Production/Stable
Classifier: Intended Audience :: Developers
Classifier: Programming Language :: Other
Classifier: Programming Language :: Python :: 3
Classifier: Programming Language :: Python :: 3.6
Classifier: Programming Language :: Python :: 3.7
Classifier: Programming Language :: Python :: 3.8
Classifier: Programming Language :: Python :: 3.9
Classifier: Programming Language :: Python :: 3.10
Classifier: Programming Language :: Python :: 3.11
Classifier: License :: OSI Approved :: MIT License
Classifier: Operating System :: OS Independent
Classifier: Topic :: Software Development
Classifier: Topic :: Software Development :: Interpreters
Classifier: Topic :: Software Development :: Libraries :: Python Modules
Requires-Python: ~=3.6
License-File: LICENSE.txt
Requires-Dist: antlr4-python3-runtime (>=4.10.1)
